src/verilog/MisterSdram32MBController.v
module MisterSdram32MBController #(
  parameter NOP_SLOTS = 5,
  parameter REFRESH_AT = 300
) (
  input             clk,
  input             rst,
  inout      [15:0] sdram_dq,
  output reg [11:0] sdram_a = 0,
  output reg        sdram_we = 1,
  output reg        sdram_cas = 1,
  output reg        sdram_ras = 1,
  output reg        sdram_cs1 = 0,
  output reg [1:0]  sdram_ba = 0,
  output reg        sdram_clk = 0,
  input             writeport_wr,
  input      [31:0] writeport_addr,
  input      [15:0] writeport_data,
  output reg        writeport_ack = 0,
  input             readport_rd,
  input      [31:0] readport_addr,
  output reg [15:0] readport_data = 0,
//   input             readport_next,
  output reg        readport_ack = 0
);
reg [3:0] setup_state = 1;
reg [3:0] refresh_state = 0;
reg [3:0] write_state = 0;
reg [3:0] read_state = 0;
reg [31:0] refresh_counter = 0;
reg [31:0] wt_cnt = 0;
reg [15:0] latched_addr = 0;
reg [31:0] latched_data = 0;
reg [15:0] sdram_dq_reg = 0;
reg writing = 0;
assign sdram_dq = writing ? sdram_dq_reg : 16'bZ;

`define INIT_WAIT wt_cnt <= 0;
`define WAIT_NOP_SLOTS(done) `ISSUE_NOP; if (wt_cnt == NOP_SLOTS) begin; done; end \
    else begin; wt_cnt <= wt_cnt + 1; end
`define ISSUE_NOP sdram_we <= 1; sdram_cas <= 1; sdram_ras <= 1; writing <= 0;
`define ISSUE_REFRESH sdram_we <= 1; sdram_cas <= 0; sdram_ras <= 0;
`define ISSUE_BANK_ACTIVATE sdram_we <= 1; sdram_cas <= 1; sdram_ras <= 0; \
    sdram_ba <= latched_addr[24:23]; sdram_a <= latched_addr[22:13];
`define ISSUE_WRITE sdram_we <= 0; sdram_cas <= 0; sdram_ras <= 1; \
    sdram_a <= latched_addr[9:0]; sdram_dq_reg <= latched_data; writing <= 1;
`define ISSUE_READ sdram_we <= 1; sdram_cas <= 0; sdram_ras <= 1; \
    sdram_ba <= latched_addr[24:23]; sdram_a <= 12'h400 + latched_addr[9:0];
`define ISSUE_PRECHARGE_ALL sdram_we <= 0; sdram_cas <= 1; sdram_ras <= 0; sdram_a <= 12'h400;
`define ISSUE_MODE_REGISTER_SET sdram_we <= 0; sdram_cas <= 0; sdram_ras <= 0; \
    sdram_a <= 12'b001000110000; sdram_ba <= 2'b00;
always @(posedge clk) begin
    if (sdram_clk) begin
        if (setup_state != 0) begin
            if (setup_state == 1) begin
                `ISSUE_NOP
                setup_state <= 2;
                `INIT_WAIT
            end else if (setup_state == 2) begin
                `WAIT_NOP_SLOTS(setup_state <= 3)
            end else if (setup_state == 3) begin
                `ISSUE_PRECHARGE_ALL
                setup_state <= 4;
                `INIT_WAIT
            end else if (setup_state == 4) begin
                `WAIT_NOP_SLOTS(setup_state <= 5)
            end else if (setup_state == 5) begin
                `ISSUE_REFRESH
                setup_state <= 6;
                `INIT_WAIT
            end else if (setup_state == 6) begin
                `WAIT_NOP_SLOTS(setup_state <= 7)
            end else if (setup_state == 7) begin
                `ISSUE_REFRESH
                setup_state <= 8;
                `INIT_WAIT
            end else if (setup_state == 8) begin
                `WAIT_NOP_SLOTS(setup_state <= 9)
            end else if (setup_state == 9) begin
                `ISSUE_MODE_REGISTER_SET
                setup_state <= 10;
                `INIT_WAIT
            end else if (setup_state == 10) begin
                `WAIT_NOP_SLOTS(setup_state <= 0)
            end
        end else if (refresh_state != 0) begin
            if (refresh_state == 1) begin
                `ISSUE_REFRESH
                refresh_state <= 2;
                `INIT_WAIT
            end else begin
                `WAIT_NOP_SLOTS(refresh_state <= 0)
            end
        end else if (write_state != 0) begin
            if (write_state == 1) begin // Activate
                `ISSUE_BANK_ACTIVATE
                write_state <= 2;
                `INIT_WAIT
            end else if (write_state == 2) begin
                `WAIT_NOP_SLOTS(write_state <= 3)
            end else if (write_state == 3) begin
                `ISSUE_WRITE
                write_state <= 4;
                `INIT_WAIT
            end else if (write_state == 4) begin
                `WAIT_NOP_SLOTS(write_state <= 5)
            end else if (write_state == 5) begin
                `ISSUE_PRECHARGE_ALL
                write_state <= 6;
                `INIT_WAIT
            end else if (write_state == 6) begin
                `WAIT_NOP_SLOTS(write_state <= 7)
            end else if (write_state == 7) begin
                if (!writeport_wr) begin
                    writeport_ack <= 0;
                    write_state <= 0;
                end else begin
                    writeport_ack <= 1;
                end
            end
        end else if (read_state != 0) begin
            if (read_state == 1) begin // Activate
                `ISSUE_BANK_ACTIVATE
                read_state <= 2;
                `INIT_WAIT
            end else if (read_state == 2) begin
                `WAIT_NOP_SLOTS(read_state <= 3)
            end else if (read_state == 3) begin
                `ISSUE_READ
                read_state <= 4;
                `INIT_WAIT
            end else if (read_state == 4) begin
                `WAIT_NOP_SLOTS(read_state <= 5)
                readport_data <= sdram_dq;
            end else if (write_state == 5) begin
                `ISSUE_PRECHARGE_ALL
                read_state <= 6;
                `INIT_WAIT
            end else if (read_state == 6) begin
                `WAIT_NOP_SLOTS(read_state <= 7)
            end else if (read_state == 7) begin
                if (!readport_rd) begin
                    readport_ack <= 0;
                    read_state <= 0;
                end else begin
                    readport_ack <= 1;
                end
            end
        end else if (refresh_counter > REFRESH_AT) begin // QUESTION: Can a refresh squeeze in before a cart read in time???
            refresh_state <= 1;
            refresh_counter <= 0;
        end else if (writeport_wr) begin
            latched_addr <= writeport_addr;
            latched_data <= writeport_data;
            write_state <= 1;
        end else if (readport_rd) begin
            latched_addr <= writeport_addr;
            read_state <= 1;
        end else begin
            refresh_counter <= refresh_counter + 1;
        end
    end
    sdram_clk <= ~sdram_clk;
end
endmodule

tmp/testbench.sv
`timescale 1ns / 1ps
module MisterSdram32MBController_testbench;
    reg clk = 0;
    reg rst = 0;
    reg [15:0] sdram_dq;
    wire [11:0] sdram_a;
    wire sdram_we;
    wire sdram_cas;
    wire sdram_ras;
    wire sdram_cs1;
    wire [1:0] sdram_ba;
    wire sdram_clk;
    reg writeport_wr;
    reg [31:0] writeport_addr = 0;
    reg [15:0] writeport_data = 0;
    wire writeport_ack;
    reg readport_rd = 0;
    reg [31:0] readport_addr = 0;
    wire [15:0] readport_data;
    // reg readport_next = 0;
    wire readport_ack;
    MisterSdram32MBController MisterSdram32MBController_0(
        .clk(clk),
        .rst(rst),
        .sdram_dq(sdram_dq),
        .sdram_a(sdram_a),
        .sdram_we(sdram_we),
        .sdram_cas(sdram_cas),
        .sdram_ras(sdram_ras),
        .sdram_cs1(sdram_cs1),
        .sdram_ba(sdram_ba),
        .sdram_clk(sdram_clk),
        .writeport_wr(writeport_wr),
        .writeport_addr(writeport_addr),
        .writeport_data(writeport_data),
        .writeport_ack(writeport_ack),
        .readport_rd(readport_rd),
        .readport_addr(readport_addr),
        .readport_data(readport_data),
        // .readport_next(readport_next),
        .readport_ack(readport_ack)
    );
    initial
    begin
        $dumpfile("dump.vcd");
        $dumpvars(5);
        #10
        // write = 1; // Set AD direction to write
        // N64_AD_o = 16'h0000; N64_ALE_H = 0; #10 // Clock in address high
        // N64_AD_o = 16'h0000; N64_ALE_L = 0; #10 // Clock in address low
        // write = 0; // Set AD direction to read
        // N64_READ_N = 0; #10 // Clock in read
        // N64_READ_N = 1; #10 N64_READ_N = 0; #10 // Clock in next read
        // N64_READ_N = 1; #10 N64_READ_N = 0; #10 // Clock in next read
        // N64_READ_N = 1; #10 N64_READ_N = 0; #10 // Clock in next read
        // N64_ALE_H = 1; N64_ALE_L = 1; N64_READ_N = 1; #10 // Reset for next burst
        // write = 1; // Set AD direction to write
        // N64_AD_o = 16'h0001; N64_ALE_H = 0; #10 // Clock in address high
        // N64_AD_o = 16'hB420; N64_ALE_L = 0; #10 // Clock in address low
        // write = 0; // Set AD direction to read
        // N64_READ_N = 0; #10 // Clock in read
        // N64_READ_N = 1; #10 N64_READ_N = 0; #10 // Clock in next read
        // N64_READ_N = 1; #10 N64_READ_N = 0; #10 // Clock in next read
        // N64_READ_N = 1; #10 N64_READ_N = 0; #10 // Clock in next read
        
        #10000;
        $finish();
    end
    always #1 begin
        clk = ~clk;
    end
endmodule


// `timescale 1ns / 1ps
// module MainWrapper_testbench;
//     reg clk = 0;
//     wire [15:0] N64_AD;
//     reg [15:0] N64_AD_o;
//     reg write = 0;
//     assign N64_AD = (write == 1) ? N64_AD_o : 16'bZ;
//     reg N64_READ_N = 1;
//     reg N64_ALE_H = 1;
//     reg N64_ALE_L = 1;
//     wire N64_INT;
//     Main Main_0(
//         .clk(clk),
//         .N64_AD(N64_AD),
//         .N64_READ_N(N64_READ_N),
//         .N64_ALE_H(N64_ALE_H),
//         .N64_ALE_L(N64_ALE_L),
//         .N64_INT4(N64_INT4)
//     );
//     initial
//     begin
//         $dumpfile("dump.vcd");
//         $dumpvars(5);
//         #10
//         write = 1; // Set AD direction to write
//         N64_AD_o = 16'h0000; N64_ALE_H = 0; #10 // Clock in address high
//         N64_AD_o = 16'h0000; N64_ALE_L = 0; #10 // Clock in address low
//         write = 0; // Set AD direction to read
//         N64_READ_N = 0; #10 // Clock in read
//         N64_READ_N = 1; #10 N64_READ_N = 0; #10 // Clock in next read
//         N64_READ_N = 1; #10 N64_READ_N = 0; #10 // Clock in next read
//         N64_READ_N = 1; #10 N64_READ_N = 0; #10 // Clock in next read
//         N64_ALE_H = 1; N64_ALE_L = 1; N64_READ_N = 1; #10 // Reset for next burst
//         write = 1; // Set AD direction to write
//         N64_AD_o = 16'h0001; N64_ALE_H = 0; #10 // Clock in address high
//         N64_AD_o = 16'hB420; N64_ALE_L = 0; #10 // Clock in address low
//         write = 0; // Set AD direction to read
//         N64_READ_N = 0; #10 // Clock in read
//         N64_READ_N = 1; #10 N64_READ_N = 0; #10 // Clock in next read
//         N64_READ_N = 1; #10 N64_READ_N = 0; #10 // Clock in next read
//         N64_READ_N = 1; #10 N64_READ_N = 0; #10 // Clock in next read
        
//         #1000;
//         $finish();
//     end
//     always #1 begin
//         clk = ~clk;
//     end
// endmodule










// `timescale 1ns / 1ps
// module FragmentProcessorWithSRAMInterface_testbench;
//   reg clock = 0;
//   reg reset = 0;
//   wire [31:0] io_bram_addr_a;
//   wire [31:0] io_bram_wrdata_a;
//   reg [31:0] io_bram_rddata_a = 0;
//   wire io_bram_en_a;
//   wire io_bram_we_a;
//   FragmentProcessorWithSRAMInterface FragmentProcessorWithSRAMInterface_inst(
//      .clock(clock)
//     ,.reset(reset)
//     ,.io_bram_addr_a(io_bram_addr_a)
//     ,.io_bram_wrdata_a(io_bram_wrdata_a)
//     ,.io_bram_rddata_a(io_bram_rddata_a)
//     ,.io_bram_en_a(io_bram_en_a)
//     ,.io_bram_we_a(io_bram_we_a)
//   );
//   reg [31:0] fake_bram1 [31:0];
//   reg [31:0] fake_bram2 [31:0];
//   reg which_bram = 0;
//   initial begin
//     $readmemh("fake_bram.list", fake_bram1);
//     $readmemh("fake_bram2.list", fake_bram2);
//     $dumpfile("dump.vcd");
//     $dumpvars(5);
//     reset = 1; #10 reset = 0;
//     $writememh("fake_bram_before.list", fake_bram1);
//     #1000;
//     $writememh("fake_bram_after1.list", fake_bram1);
//     which_bram = 1;
//     // $readmemh("fake_bram2.list", fake_bram);
//     #1000;
//     $writememh("fake_bram_after2.list", fake_bram2);
//     $finish();
//   end
//   always #1 begin
//     clock = ~clock;
//     if (io_bram_en_a) begin
//       if (io_bram_we_a) begin
//         if (which_bram) begin
//           fake_bram2[io_bram_addr_a >> 2] <= io_bram_wrdata_a;
//         end
//         else
//         begin
//           fake_bram1[io_bram_addr_a >> 2] <= io_bram_wrdata_a;
//         end
//       end
//       else begin
//         if (which_bram) begin
//           io_bram_rddata_a <= fake_bram2[io_bram_addr_a >> 2];
//         end
//         else
//         begin
//           io_bram_rddata_a <= fake_bram1[io_bram_addr_a >> 2];
//         end
//       end
//     end
//   end
// endmodule

  // input         clock,
  // input         reset,
  // output [31:0] io_bram_addr_a,
  // output [31:0] io_bram_wrdata_a,
  // input  [31:0] io_bram_rddata_a,
  // output        io_bram_en_a,
  // output        io_bram_we_a


// module spriteaccel_testbench;
//   reg clk = 0;
//   reg resetn = 0;
//   reg [31:0] awaddr = 0;
//   reg awvalid = 0;
//   wire awready;
//   reg [31:0] wdata = 0;
//   reg [3:0] wstrb = 0;
//   reg wvalid = 0;
//   wire wready;
//   reg [31:0] araddr = 0;
//   reg arvalid = 0;
//   wire arready;
//   wire [31:0] rdata;
//   wire [1:0] rresp;
//   wire rvalid;
//   reg rready = 0;
//   wire [1:0] bresp;
//   wire bvalid;
//   reg bready = 0;

//   axi4lite_top axi4lite_top_inst (
//     .S_AXI_ACLK(clk),
//     .S_AXI_ARESETN(resetn),
//     .S_AXI_AWADDR(awaddr),
//     .S_AXI_AWVALID(awvalid),
//     .S_AXI_AWREADY(awready),
//     .S_AXI_WDATA(wdata),
//     .S_AXI_WSTRB(wstrb),
//     .S_AXI_WVALID(wvalid),
//     .S_AXI_WREADY(wready),
//     .S_AXI_ARADDR(araddr),
//     .S_AXI_ARVALID(arvalid),
//     .S_AXI_ARREADY(arready),
//     .S_AXI_RDATA(rdata),
//     .S_AXI_RRESP(rresp),
//     .S_AXI_RVALID(rvalid),
//     .S_AXI_RREADY(rready),
//     .S_AXI_BRESP(bresp),
//     .S_AXI_BVALID(bvalid),
//     .S_AXI_BREADY(bready)
//   );

//   initial begin
//     $dumpfile("dump.vcd");
//     $dumpvars(1);
//   end

//   always #1 clk = ~clk;

//   initial begin
//     resetn = 0; #10 resetn = 1;
//     #10
//     awaddr <= 32'h000000;
//     wdata <= 32'h5a5a5a5a;
//     awvalid <= 1;
//     wvalid <= 1;
//     rready <= 1;
//     wstrb <= 4'hF;


//     //     #3 write_addr <= addr;  //Put write address on bus
//     // write_data <= data; //put write data on bus
//     // write_addr_valid <= 1'b1; //indicate address is valid
//     // write_data_valid <= 1'b1; //indicate data is valid
//     // write_resp_ready <= 1'b1; //indicate ready for a response
//     // write_strb <= 4'hF;   //writing all 4 bytes


//     #1000;
//     $finish();
//   end
// endmodule



// // `define NUM_SCANLINES 480
// // `define SCANLINE_SIZE 640
// // `define SPRITETABLE_SIZE 256
// // `define TILEDATA_SIZE 256
// // `define NUM_PALETTES 4
// // `define NUM_BACKGROUNDS 2

// // `define SPRITEACCEL memory_widener_inst.memory_merger_inst.spriteaccel_inst

// // `define BACKGROUND_MEM_SIZE `NUM_BACKGROUNDS * 64 * 64 * 2 + `NUM_BACKGROUNDS * 4

// // `define WRITE_MEM(address2, value) write_request = 1;\
// //   address = ``address2``;\
// //   write_data = ``value``;\
// //   #20\
// //   write_request = 0

// // `define ASSERT_MEM(address2, value) read_request = 1;\
// //   address = ``address2``;\
// //   #30\
// //   assert_temp = read_data;\
// //   read_request = 0;\
// //   #30\
// //   if (assert_temp != ``value``) $display("%H %H", assert_temp, ``value``)

// // `define WRITE_MEM_4(address2, value1, value2, value3, value4)\
// //   #10\
// //   `WRITE_MEM(``address2``, ``value1`` + (``value2`` << 8) + (``value3`` << 16) + (``value4`` << 24))

// // `define WRITE_SPRITE(index, x, y, width, height, tile_index, pallete_index)\
// //   `WRITE_MEM_4(\
// //     `SPRITETABLE_MEM_OFFSET + ``index`` * `SPRITETABLE_ITEM_SIZE + `SPRITETABLE_ITEM_X_OFFSET_LO,\
// //     ``x`` & 8'hFF,\
// //     (``x`` >> 8) & 8'hFF,\
// //     ``y`` & 8'hFF,\
// //     (``y`` >> 8) & 8'hFF\
// //   );\
// //   `WRITE_MEM_4(\
// //     `SPRITETABLE_MEM_OFFSET + ``index`` * `SPRITETABLE_ITEM_SIZE + `SPRITETABLE_ITEM_WIDTH_OFFSET,\
// //     ``width``,\
// //     ``height``,\
// //     ``tile_index`` & 8'hFF,\
// //     (``tile_index`` >> 8) & 8'hFF\
// //   );\
// //   `WRITE_MEM_4(\
// //     `SPRITETABLE_MEM_OFFSET + ``index`` * `SPRITETABLE_ITEM_SIZE + `SPRITETABLE_ITEM_WIDTH_OFFSET,\
// //     ``width``,\
// //     ``height``,\
// //     ``tile_index`` & 8'hFF,\
// //     (``tile_index`` >> 8) & 8'hFF\
// //   );\
// //   `WRITE_MEM_4(\
// //     `SPRITETABLE_MEM_OFFSET + ``index`` * `SPRITETABLE_ITEM_SIZE + `SPRITETABLE_ITEM_PALETTE_INDEX,\
// //     0,\
// //     0,\
// //     0,\
// //     ``pallete_index``\
// //   )

// // `define MEMORY_PORT(prefix, memory_size)\
// //   reg ``prefix``_read_request = 0;\
// //   reg ``prefix``_read_success;\
// //   reg ``prefix``_write_request = 0;\
// //   reg ``prefix``_write_success;\
// //   reg [$clog2(``memory_size``)-1:0] ``prefix``_address = 0;\
// //   reg [31:0] ``prefix``_read_data;\
// //   reg [31:0] ``prefix``_write_data = 0

// // `define MEMORY_CONNECTION(prefix)\
// //   .``prefix``_read_request(``prefix``_read_request),\
// //   .``prefix``_read_success(``prefix``_read_success),\
// //   .``prefix``_write_request(``prefix``_write_request),\
// //   .``prefix``_write_success(``prefix``_write_success),\
// //   .``prefix``_address(``prefix``_address),\
// //   .``prefix``_read_data(``prefix``_read_data),\
// //   .``prefix``_write_data(``prefix``_write_data)

// // module spriteaccel_testbench;
// //   string CURRENT_TEST_NAME;
// //   integer i;
// //   integer j;
// //   integer outfile;
  
// //   reg clock = 0;
// //   reg reset = 0;
// //   reg read_request = 0;
// //   reg write_request = 0;
// //   wire read_success;
// //   wire write_success;
// //   reg [31:0] address = 0;
// //   reg [31:0] write_data = 0;
// //   reg [3:0] write_strobe = 0;
// //   reg [31:0] read_data;

// //   wire [4:0] state = memory_widener_inst.state;
// //   wire [31:0] read_data_r = memory_widener_inst.read_data_r;
// //   wire [7:0] aaa = memory_widener_inst.mm_read_data;
// //   wire [7:0] bbb = memory_widener_inst.memory_merger_inst.read_data;
// //   wire [7:0] ccc = memory_widener_inst.memory_merger_inst.control_read_data;

// //   reg [31:0] assert_temp;

// //   memory_widener #(
// //     .num_scanlines(`NUM_SCANLINES),
// //     .scanline_size(`SCANLINE_SIZE),
// //     .spritetable_size(`SPRITETABLE_SIZE),
// //     .tiledata_size(`TILEDATA_SIZE),
// //     .num_palettes(`NUM_PALETTES),
// //     .num_backgrounds(`NUM_BACKGROUNDS)
// //   ) memory_widener_inst (
// //     .clock(clock),
// //     .reset(reset),
// //     .read_request(read_request),
// //     .read_success(read_success),
// //     .write_request(write_request),
// //     .write_success(write_success),
// //     .address(address),
// //     .write_data(write_data),
// //     .write_strobe(write_strobe),
// //     .read_data(read_data)
// //   );

// //   initial begin
// //     $dumpfile("dump.vcd");
// //     $dumpvars(1);
// //   end

// //   always #1 clock = ~clock;

// //   initial begin

// //     $display("scanline_memory size:", $size(`SPRITEACCEL.scanline_memory));
// //     $display("control_memory size:", $size(`SPRITEACCEL.control_memory));

// //     // Initialize memory to zeroes
// //     for(i = 0; i < `SCANLINE_SIZE * 3; i++) begin
// //       `SPRITEACCEL.scanline_memory[i] = 8'h00;
// //     end
// //     for(i = 0; i < `SPRITETABLE_SIZE * `SPRITETABLE_ITEM_SIZE; i++) begin
// //       `SPRITEACCEL.spritetable_memory[i] = 8'h00;
// //     end
// //     for(i = 0; i < `TILEDATA_SIZE * 8 * 8; i++) begin
// //       `SPRITEACCEL.tiledata_memory[i] = 8'h00;
// //     end
// //     for(i = 0; i < `NUM_PALETTES * 256 * 2; i++) begin
// //       `SPRITEACCEL.palette_memory[i] = 8'h00;
// //     end
// //     for(i = 0; i < `BACKGROUND_MEM_SIZE; i++) begin
// //       `SPRITEACCEL.background_memory[i] = 8'h00;
// //     end
// //     for(i = 0; i < `SETTINGS_MEMORY_SIZE; i++) begin
// //       `SPRITEACCEL.settings_memory[i] = 8'h00;
// //     end
// //     for(i = 0; i < `CONTROL_MEMORY_SIZE; i++) begin
// //       `SPRITEACCEL.control_memory[i] = 8'h00;
// //     end

// //     reset = 1; #10 reset = 0;

// //     // Test read/write functionality
// //     `WRITE_MEM(`SCANLINE_MEM_OFFSET + 4, 32'h11223344);
// //     #10
// //     `ASSERT_MEM(`SCANLINE_MEM_OFFSET + 4, 32'h11223344);
// //     #10
// //     `WRITE_MEM(`SPRITETABLE_MEM_OFFSET + 4, 32'h11223344);
// //     #10
// //     `ASSERT_MEM(`SPRITETABLE_MEM_OFFSET + 4, 32'h11223344);
// //     #10
// //     `WRITE_MEM(`TILEDATA_MEM_OFFSET + 4, 32'h11223344);
// //     #10
// //     `ASSERT_MEM(`TILEDATA_MEM_OFFSET + 4, 32'h11223344);
// //     #10
// //     `WRITE_MEM(`PALETTE_MEM_OFFSET + 4, 32'h11223344);
// //     #10
// //     `ASSERT_MEM(`PALETTE_MEM_OFFSET + 4, 32'h11223344);
// //     #10
// //     `WRITE_MEM(`BACKGROUND_MEM_OFFSET + 4, 32'h11223344);
// //     #10
// //     `ASSERT_MEM(`BACKGROUND_MEM_OFFSET + 4, 32'h11223344);
// //     #10
// //     `WRITE_MEM(`SETTINGS_MEM_OFFSET + 4, 32'h11223344);
// //     #10
// //     `ASSERT_MEM(`SETTINGS_MEM_OFFSET + 4, 32'h11223344);
// //     #10

// //     // Load in data
// //     $readmemh("spritetable_rom.list", `SPRITEACCEL.spritetable_memory);
// //     $readmemh("sprite_rom.list", `SPRITEACCEL.tiledata_memory);
// //     $readmemh("palette_rom.list", `SPRITEACCEL.palette_memory);
// //     $readmemh("background_rom.list", `SPRITEACCEL.background_memory);
// //     #10

// //     outfile = $fopen("scanlines.output.list");

// //     for(i = 0; i < `NUM_SCANLINES; i++) begin
// //       // Set scanline number
// //       `WRITE_MEM(`CONTROL_MEM_OFFSET + `CONTROL_MEMORY_SCANLINE_NUMBER_HI, (i & 16'hff00) >> 8);
// //       #10
// //       `WRITE_MEM(`CONTROL_MEM_OFFSET + `CONTROL_MEMORY_SCANLINE_NUMBER_LO, i & 8'hff);
// //       #100
// //       // Kick off a run
// //       `WRITE_MEM(`CONTROL_MEM_OFFSET + `CONTROL_MEMORY_RUN_OFFSET, 8'hff);
// //       #8000
// //       for (j = 0; j < (`SCANLINE_SIZE * 3); j += 3) begin
// //         $fwrite(outfile, "%02x%02x%02x",
// //           `SPRITEACCEL.scanline_memory[j],
// //           `SPRITEACCEL.scanline_memory[j + 1],
// //           `SPRITEACCEL.scanline_memory[j + 2]
// //         );
// //         if (j != (`SCANLINE_SIZE * 3) - 1) $fwrite(outfile, " ");
// //       end
// //       $fwrite(outfile, "\n");
// //     end

// //     $finish();
// //   end
// // endmodule

tmp/dump.vcd
$date
	Fri Mar 11 19:18:28 2022
$end
$version
	Icarus Verilog
$end
$timescale
	1ps
$end
$scope module MisterSdram32MBController_testbench $end
$var wire 1 ! writeport_ack $end
$var wire 1 " sdram_we $end
$var wire 1 # sdram_ras $end
$var wire 16 $ sdram_dq [15:0] $end
$var wire 1 % sdram_cs1 $end
$var wire 1 & sdram_clk $end
$var wire 1 ' sdram_cas $end
$var wire 2 ( sdram_ba [1:0] $end
$var wire 12 ) sdram_a [11:0] $end
$var wire 16 * readport_data [15:0] $end
$var wire 1 + readport_ack $end
$var reg 1 , clk $end
$var reg 32 - readport_addr [31:0] $end
$var reg 1 . readport_rd $end
$var reg 1 / rst $end
$var reg 32 0 writeport_addr [31:0] $end
$var reg 16 1 writeport_data [15:0] $end
$var reg 1 2 writeport_wr $end
$scope module MisterSdram32MBController_0 $end
$var wire 1 , clk $end
$var wire 32 3 readport_addr [31:0] $end
$var wire 1 . readport_rd $end
$var wire 1 / rst $end
$var wire 32 4 writeport_addr [31:0] $end
$var wire 16 5 writeport_data [15:0] $end
$var wire 1 2 writeport_wr $end
$var wire 16 6 sdram_dq [15:0] $end
$var reg 16 7 latched_addr [15:0] $end
$var reg 32 8 latched_data [31:0] $end
$var reg 4 9 read_state [3:0] $end
$var reg 1 + readport_ack $end
$var reg 16 : readport_data [15:0] $end
$var reg 32 ; refresh_counter [31:0] $end
$var reg 4 < refresh_state [3:0] $end
$var reg 12 = sdram_a [11:0] $end
$var reg 2 > sdram_ba [1:0] $end
$var reg 1 ' sdram_cas $end
$var reg 1 & sdram_clk $end
$var reg 1 % sdram_cs1 $end
$var reg 16 ? sdram_dq_reg [15:0] $end
$var reg 1 # sdram_ras $end
$var reg 1 " sdram_we $end
$var reg 4 @ setup_state [3:0] $end
$var reg 4 A write_state [3:0] $end
$var reg 1 ! writeport_ack $end
$var reg 1 B writing $end
$var reg 32 C wt_cnt [31:0] $end
$upscope $end
$upscope $end
$enddefinitions $end
#0
$dumpvars
b0 C
0B
b0 A
b1 @
b0 ?
b0 >
b0 =
b0 <
b0 ;
b0 :
b0 9
b0 8
b0 7
bz 6
b0 5
b0 4
b0 3
x2
b0 1
b0 0
0/
0.
b0 -
0,
0+
b0 *
b0 )
b0 (
1'
0&
0%
bz $
1#
1"
0!
$end
#1000
1&
1,
#2000
0,
#3000
0&
b10 @
1,
#4000
0,
#5000
1&
1,
#6000
0,
#7000
0&
b1 C
1,
#8000
0,
#9000
1&
1,
#10000
0,
#11000
0&
b10 C
1,
#12000
0,
#13000
1&
1,
#14000
0,
#15000
0&
b11 C
1,
#16000
0,
#17000
1&
1,
#18000
0,
#19000
0&
b100 C
1,
#20000
0,
#21000
1&
1,
#22000
0,
#23000
0&
b101 C
1,
#24000
0,
#25000
1&
1,
#26000
0,
#27000
0&
b11 @
1,
#28000
0,
#29000
1&
1,
#30000
0,
#31000
0&
b0 C
b100 @
b10000000000 )
b10000000000 =
0#
0"
1,
#32000
0,
#33000
1&
1,
#34000
0,
#35000
0&
b1 C
1#
1"
1,
#36000
0,
#37000
1&
1,
#38000
0,
#39000
0&
b10 C
1,
#40000
0,
#41000
1&
1,
#42000
0,
#43000
0&
b11 C
1,
#44000
0,
#45000
1&
1,
#46000
0,
#47000
0&
b100 C
1,
#48000
0,
#49000
1&
1,
#50000
0,
#51000
0&
b101 C
1,
#52000
0,
#53000
1&
1,
#54000
0,
#55000
0&
b101 @
1,
#56000
0,
#57000
1&
1,
#58000
0,
#59000
0&
b0 C
b110 @
0#
0'
1,
#60000
0,
#61000
1&
1,
#62000
0,
#63000
0&
b1 C
1#
1'
1,
#64000
0,
#65000
1&
1,
#66000
0,
#67000
0&
b10 C
1,
#68000
0,
#69000
1&
1,
#70000
0,
#71000
0&
b11 C
1,
#72000
0,
#73000
1&
1,
#74000
0,
#75000
0&
b100 C
1,
#76000
0,
#77000
1&
1,
#78000
0,
#79000
0&
b101 C
1,
#80000
0,
#81000
1&
1,
#82000
0,
#83000
0&
b111 @
1,
#84000
0,
#85000
1&
1,
#86000
0,
#87000
0&
b0 C
b1000 @
0#
0'
1,
#88000
0,
#89000
1&
1,
#90000
0,
#91000
0&
b1 C
1#
1'
1,
#92000
0,
#93000
1&
1,
#94000
0,
#95000
0&
b10 C
1,
#96000
0,
#97000
1&
1,
#98000
0,
#99000
0&
b11 C
1,
#100000
0,
#101000
1&
1,
#102000
0,
#103000
0&
b100 C
1,
#104000
0,
#105000
1&
1,
#106000
0,
#107000
0&
b101 C
1,
#108000
0,
#109000
1&
1,
#110000
0,
#111000
0&
b1001 @
1,
#112000
0,
#113000
1&
1,
#114000
0,
#115000
0&
b0 C
b1010 @
b1000110000 )
b1000110000 =
0#
0'
0"
1,
#116000
0,
#117000
1&
1,
#118000
0,
#119000
0&
b1 C
1#
1'
1"
1,
#120000
0,
#121000
1&
1,
#122000
0,
#123000
0&
b10 C
1,
#124000
0,
#125000
1&
1,
#126000
0,
#127000
0&
b11 C
1,
#128000
0,
#129000
1&
1,
#130000
0,
#131000
0&
b100 C
1,
#132000
0,
#133000
1&
1,
#134000
0,
#135000
0&
b101 C
1,
#136000
0,
#137000
1&
1,
#138000
0,
#139000
0&
b0 @
1,
#140000
0,
#141000
1&
1,
#142000
0,
#143000
0&
b1 ;
1,
#144000
0,
#145000
1&
1,
#146000
0,
#147000
0&
b10 ;
1,
#148000
0,
#149000
1&
1,
#150000
0,
#151000
0&
b11 ;
1,
#152000
0,
#153000
1&
1,
#154000
0,
#155000
0&
b100 ;
1,
#156000
0,
#157000
1&
1,
#158000
0,
#159000
0&
b101 ;
1,
#160000
0,
#161000
1&
1,
#162000
0,
#163000
0&
b110 ;
1,
#164000
0,
#165000
1&
1,
#166000
0,
#167000
0&
b111 ;
1,
#168000
0,
#169000
1&
1,
#170000
0,
#171000
0&
b1000 ;
1,
#172000
0,
#173000
1&
1,
#174000
0,
#175000
0&
b1001 ;
1,
#176000
0,
#177000
1&
1,
#178000
0,
#179000
0&
b1010 ;
1,
#180000
0,
#181000
1&
1,
#182000
0,
#183000
0&
b1011 ;
1,
#184000
0,
#185000
1&
1,
#186000
0,
#187000
0&
b1100 ;
1,
#188000
0,
#189000
1&
1,
#190000
0,
#191000
0&
b1101 ;
1,
#192000
0,
#193000
1&
1,
#194000
0,
#195000
0&
b1110 ;
1,
#196000
0,
#197000
1&
1,
#198000
0,
#199000
0&
b1111 ;
1,
#200000
0,
#201000
1&
1,
#202000
0,
#203000
0&
b10000 ;
1,
#204000
0,
#205000
1&
1,
#206000
0,
#207000
0&
b10001 ;
1,
#208000
0,
#209000
1&
1,
#210000
0,
#211000
0&
b10010 ;
1,
#212000
0,
#213000
1&
1,
#214000
0,
#215000
0&
b10011 ;
1,
#216000
0,
#217000
1&
1,
#218000
0,
#219000
0&
b10100 ;
1,
#220000
0,
#221000
1&
1,
#222000
0,
#223000
0&
b10101 ;
1,
#224000
0,
#225000
1&
1,
#226000
0,
#227000
0&
b10110 ;
1,
#228000
0,
#229000
1&
1,
#230000
0,
#231000
0&
b10111 ;
1,
#232000
0,
#233000
1&
1,
#234000
0,
#235000
0&
b11000 ;
1,
#236000
0,
#237000
1&
1,
#238000
0,
#239000
0&
b11001 ;
1,
#240000
0,
#241000
1&
1,
#242000
0,
#243000
0&
b11010 ;
1,
#244000
0,
#245000
1&
1,
